{
  "type": "forge:conditional",
  "recipes": [
    {
      "conditions": [
        {
          "values": [
            {
              "modid": "farmersdelight",
              "type": "forge:mod_loaded"
            },
            {
              "item": "netherdepthsupgrade:obsidianfish_slice",
              "type": "forge:item_exists"
            },
            {
              "item": "netherdepthsupgrade:baked_obsidianfish_stew",
              "type": "forge:item_exists"
            }
          ],
          "type": "forge:and"
        }
      ],
      "recipe": {
        "type": "farmersdelight:cooking",
        "ingredients": [
          {
            "item": "netherdepthsupgrade:obsidianfish_slice"
          },
          {
            "item": "minecraft:potato"
          },
          {
            "tag": "forge:eggs"
          },
          {
            "tag": "forge:crops/tomato"
          }
        ],
        "result": {
          "item": "netherdepthsupgrade:baked_obsidianfish_stew"
        },
        "experience": 0.35,
        "cookingtime": 200
      }
    }
  ]
}